ISStreamer/Streamer.py
ISStreamer/__init__.py
ISStreamer/configutil.py
ISStreamer/version.py
ISStreamer-2.0.0.dist-info/LICENSE.txt
ISStreamer-2.0.0.dist-info/METADATA
ISStreamer-2.0.0.dist-info/WHEEL
ISStreamer-2.0.0.dist-info/top_level.txt
ISStreamer-2.0.0.dist-info/RECORD
