Metadata-Version: 2.1
Name: ISStreamer
Version: 2.0.0
Summary: A python module to simplify the process of getting log data to Initial State's platform
Home-page: https://www.initialstate.com
Author: David Sulpy, Initial State Technologies
Author-email: david@initialstate.com
License: MIT
Keywords: logger,logstream,initial state
Classifier: Development Status :: 5 - Production/Stable
Classifier: Topic :: Utilities
Classifier: License :: OSI Approved :: MIT License
License-File: LICENSE.txt
